{
  "rows": [
    {
      "sc": "RO",
      "sup": "AP",
      "employeeName": "Preston, Amy",
      "account": "FM 00360 STADIUM",
      "storeNum": 360,
      "district": 1,
      "serviceDay": "Mon",
      "action": "WRITE ORDER/SERVICE ",
      "pickDay": "Mon",
      "deliveryDay": "Wed",
      "routeNum": "309-040",
      "carriers": "Central Truck"
    },
    {
      "sc": "RO",
      "sup": "AP",
      "employeeName": "Preston, Amy",
      "account": "FM 00360 STADIUM",
      "storeNum": 360,
      "district": 1,
      "serviceDay": "Wed",
      "action": "WORK LOAD/SERVICE",
      "pickDay": null,
      "deliveryDay": null,
      "routeNum": null,
      "carriers": null
    }
  ]
}
